karrio/mappers/teleship/__init__.py
karrio/mappers/teleship/hooks.py
karrio/mappers/teleship/mapper.py
karrio/mappers/teleship/proxy.py
karrio/mappers/teleship/settings.py
karrio/plugins/teleship/__init__.py
karrio/providers/teleship/__init__.py
karrio/providers/teleship/duties.py
karrio/providers/teleship/error.py
karrio/providers/teleship/manifest.py
karrio/providers/teleship/rate.py
karrio/providers/teleship/tracking.py
karrio/providers/teleship/units.py
karrio/providers/teleship/utils.py
karrio/providers/teleship/hooks/__init__.py
karrio/providers/teleship/hooks/event.py
karrio/providers/teleship/hooks/oauth.py
karrio/providers/teleship/pickup/__init__.py
karrio/providers/teleship/pickup/cancel.py
karrio/providers/teleship/pickup/schedule.py
karrio/providers/teleship/shipment/__init__.py
karrio/providers/teleship/shipment/cancel.py
karrio/providers/teleship/shipment/create.py
karrio/providers/teleship/webhook/__init__.py
karrio/providers/teleship/webhook/deregister.py
karrio/providers/teleship/webhook/register.py
karrio/schemas/teleship/__init__.py
karrio/schemas/teleship/duties_taxes_request.py
karrio/schemas/teleship/duties_taxes_response.py
karrio/schemas/teleship/error_response.py
karrio/schemas/teleship/manifest_request.py
karrio/schemas/teleship/manifest_response.py
karrio/schemas/teleship/pickup_request.py
karrio/schemas/teleship/pickup_response.py
karrio/schemas/teleship/rate_request.py
karrio/schemas/teleship/rate_response.py
karrio/schemas/teleship/shipment_cancel_request.py
karrio/schemas/teleship/shipment_cancel_response.py
karrio/schemas/teleship/shipment_request.py
karrio/schemas/teleship/shipment_response.py
karrio/schemas/teleship/tracking_request.py
karrio/schemas/teleship/tracking_response.py
karrio/schemas/teleship/webhook_request.py
karrio/schemas/teleship/webhook_response.py
karrio_teleship-2026.1.4.dist-info/METADATA
karrio_teleship-2026.1.4.dist-info/WHEEL
karrio_teleship-2026.1.4.dist-info/entry_points.txt
karrio_teleship-2026.1.4.dist-info/top_level.txt
karrio_teleship-2026.1.4.dist-info/RECORD
